gptgpt/__init__.py
gptgpt/configs/__init__.py
gptgpt/configs/train_config.py
gptgpt/data/__init__.py
gptgpt/data/parsers/__init__.py
gptgpt/data/parsers/medquad_parser.py
gptgpt/data/parsers/text_formatter.py
gptgpt/inference/__init__.py
gptgpt/inference/decoding_utils.py
gptgpt/inference/generation_config.py
gptgpt/inference/generator.py
gptgpt/inference/sampling.py
gptgpt/model/__init__.py
gptgpt/model/architecture/__init__.py
gptgpt/model/architecture/attention.py
gptgpt/model/architecture/decoder_block.py
gptgpt/model/architecture/embeddings.py
gptgpt/model/architecture/feedforward.py
gptgpt/model/architecture/transformer.py
gptgpt/model/configs/__init__.py
gptgpt/model/configs/model_config.py
gptgpt/tokenizer/__init__.py
gptgpt/tokenizer/tokenize_data.py
gptgpt/tokenizer/train_tokenizer.py
gptgpt/training/__init__.py
gptgpt/training/dataset.py
gptgpt/training/train.py
gptgpt/training/trainer.py
gptgpt/training/utils.py
gptgpt/utils/__init__.py
gptgpt/utils/checkpoints.py
gptgpt/utils/logging.py
gptgpt-0.2.1.dist-info/licenses/LICENSE
gptgpt-0.2.1.dist-info/METADATA
gptgpt-0.2.1.dist-info/WHEEL
gptgpt-0.2.1.dist-info/entry_points.txt
gptgpt-0.2.1.dist-info/top_level.txt
gptgpt-0.2.1.dist-info/RECORD
