Metadata-Version: 2.4
Name: gptgpt
Version: 0.2.1
Summary: A lightweight GPT-based language model framework for training custom question-answering models on any domain
Author-email: Sanjog Sigdel <sigdelsanjog@gmail.com>
Maintainer-email: Sanjog Sigdel <sigdelsanjog@gmail.com>
License: MIT License
Project-URL: Homepage, https://github.com/sigdelsanjog/gptgpt
Project-URL: Documentation, https://github.com/sigdelsanjog/gptgpt#readme
Project-URL: Repository, https://github.com/sigdelsanjog/gptgpt
Project-URL: Issues, https://github.com/sigdelsanjog/gptgpt/issues
Keywords: nlp,language-model,transformer,gpt,pytorch,qa,question-answering,training,deep-learning,custom-model
Classifier: Development Status :: 3 - Alpha
Classifier: Intended Audience :: Developers
Classifier: Intended Audience :: Science/Research
Classifier: Intended Audience :: Education
Classifier: Topic :: Scientific/Engineering :: Artificial Intelligence
Classifier: Topic :: Software Development :: Libraries :: Python Modules
Classifier: License :: OSI Approved :: MIT License
Classifier: Programming Language :: Python :: 3
Classifier: Programming Language :: Python :: 3.8
Classifier: Programming Language :: Python :: 3.9
Classifier: Programming Language :: Python :: 3.10
Classifier: Programming Language :: Python :: 3.11
Classifier: Operating System :: OS Independent
Requires-Python: >=3.8
License-File: LICENSE
Requires-Dist: torch>=2.0.0
Requires-Dist: sentencepiece>=0.1.99
Requires-Dist: numpy>=1.24.0
Requires-Dist: tqdm>=4.65.0
Provides-Extra: dev
Requires-Dist: pytest>=7.0.0; extra == "dev"
Requires-Dist: black>=22.0.0; extra == "dev"
Requires-Dist: flake8>=4.0.0; extra == "dev"
Requires-Dist: mypy>=0.950; extra == "dev"
Provides-Extra: training
Requires-Dist: tensorboard>=2.10.0; extra == "training"
Requires-Dist: wandb>=0.13.0; extra == "training"
Dynamic: license-file
